LICENSE
README.md
setup.py
colab_gradio_llm/__init__.py
colab_gradio_llm/gradio_opensource.py
gradio_opensource.egg-info/PKG-INFO
gradio_opensource.egg-info/SOURCES.txt
gradio_opensource.egg-info/dependency_links.txt
gradio_opensource.egg-info/requires.txt
gradio_opensource.egg-info/top_level.txt